models/__init__.py
models/api/__init__.py
models/api/ai_completion_models.py
models/api/ai_task_models.py
models/api/base_models.py
models/api/context_models.py
models/api/message_models.py
models/api/project_models.py
models/api/prompt_models.py
models/api/user_models.py
models/enums.py
models/model_registry.py
models/orm/__init__.py
models/orm/ai_task_orm.py
models/orm/base_orm.py
models/orm/context_orm.py
models/orm/message_orm.py
models/orm/project_orm.py
models/orm/prompt_orm.py
models/orm/user_orm.py
ai_team_shared-0.5.0.dist-info/METADATA
ai_team_shared-0.5.0.dist-info/WHEEL
ai_team_shared-0.5.0.dist-info/RECORD
